Sasta/__init__.py
Sasta/cli.py
Sasta/setup.py
Sasta-0.1.dist-info/METADATA
Sasta-0.1.dist-info/WHEEL
Sasta-0.1.dist-info/entry_points.txt
Sasta-0.1.dist-info/top_level.txt
Sasta-0.1.dist-info/RECORD
