Metadata-Version: 2.1
Name: Sasta
Version: 0.1
Summary: Hi just introducing me through cmd
Home-page: https://github.com/Sastahariharan567/Sasta
Author: Sasta Hari Haran R
Author-email: sastahariharn0567@gmail.com
